sl4ng/__init__.py
sl4ng/debug.py
sl4ng/functional.py
sl4ng/iteration.py
sl4ng/maths.py
sl4ng/persistance.py
sl4ng/stats.py
sl4ng/strings.py
sl4ng/system.py
sl4ng/types.py
sl4ng/web.py
sl4ng-0.0.1.dist-info/LICENSE
sl4ng-0.0.1.dist-info/METADATA
sl4ng-0.0.1.dist-info/WHEEL
sl4ng-0.0.1.dist-info/top_level.txt
sl4ng-0.0.1.dist-info/RECORD
