Metadata-Version: 2.1
Name: sl4ng
Version: 0.0.1
Summary: UNKNOWN
Home-page: https://tildegit.org/eli2and40/sl4ng
Author: Kenneth Elisandro
Author-email: eli2and40@tilde.club
License: MIT
Keywords: utilities productivity
Platform: UNKNOWN
Classifier: Programming Language :: Python :: 3
Classifier: License :: OSI Approved :: MIT License
Classifier: Operating System :: OS Independent
Requires: pyperclip
Requires: dill
Requires: psutil
Requires: send2trash
Requires: tqdm
Requires: filetype
Requires-Python: >=3.8
